ischemist/__init__.py
ischemist/colors.py
ischemist/plotly.py
ischemist/dev/__init__.py
ischemist/dev/generate_palette.py
ischemist/dev/visualize.py
ischemist-0.2.0.dist-info/licenses/LICENSE
ischemist-0.2.0.dist-info/METADATA
ischemist-0.2.0.dist-info/WHEEL
ischemist-0.2.0.dist-info/top_level.txt
ischemist-0.2.0.dist-info/RECORD
