Metadata-Version: 2.4
Name: ischemist
Version: 0.2.0
Summary: Add your description here
Author-email: Anton Morgunov <anton@ischemist.com>
License: MIT
Project-URL: Homepage, https://github.com/ischemist/py-style
Project-URL: Issues, https://github.com/ischemist/py-style/issues
Requires-Python: >=3.10
License-File: LICENSE
Provides-Extra: plotly
Requires-Dist: coloraide>=5.1; extra == "plotly"
Requires-Dist: numpy>=2.2.6; extra == "plotly"
Requires-Dist: plotly>=6.1.2; extra == "plotly"
Dynamic: license-file
